setup.py
pswinpy/__init__.py
pswinpy/api.py
pswinpy/http_sender.py
pswinpy/mode.py
pswinpy/request.py
pswinpy.egg-info/PKG-INFO
pswinpy.egg-info/SOURCES.txt
pswinpy.egg-info/dependency_links.txt
pswinpy.egg-info/top_level.txt