Metadata-Version: 1.0
Name: pswinpy
Version: 0.0.1
Summary: A package for sending SMS messages using the PSWinCom SMS Gateway.
Home-page: https://github.com/tormaroe/pswinpy
Author: Torbjorn Maro
Author-email: torbjorn@pswin.com
License: MIT License
Keywords: SMS
Platform: UNKNOWN
Classifier: Development Status :: 4 - Beta
Classifier: Programming Language :: Python
Classifier: Programming Language :: Python :: 3
Classifier: Intended Audience :: Developers
Classifier: Topic :: Communications :: Telephony
Classifier: Topic :: Software Development :: Libraries :: Python Modules
Classifier: License :: OSI Approved :: MIT License
Classifier: Operating System :: OS Independent
